{"assets/A+.jpg":["assets/A+.jpg"],"assets/ABB.jpg":["assets/ABB.jpg"],"assets/ABneg.jpg":["assets/ABneg.jpg"],"assets/ABpos.jpg":["assets/ABpos.jpg"],"assets/AK.jpg":["assets/AK.jpg"],"assets/Aku.jpeg":["assets/Aku.jpeg"],"assets/Amrutha.jpg":["assets/Amrutha.jpg"],"assets/Aneg.jpg":["assets/Aneg.jpg"],"assets/Blood.jpg":["assets/Blood.jpg"],"assets/Blood.png":["assets/Blood.png"],"assets/Bneg.jpg":["assets/Bneg.jpg"],"assets/Bpos.jpg":["assets/Bpos.jpg"],"assets/Dattaji.jpg":["assets/Dattaji.jpg"],"assets/GGBB.jpg":["assets/GGBB.jpg"],"assets/Jankalyan.jpg":["assets/Jankalyan.jpg"],"assets/Jeevanjyoti.jpg":["assets/Jeevanjyoti.jpg"],"assets/Lifeline.jpg":["assets/Lifeline.jpg"],"assets/O+.jpg":["assets/O+.jpg"],"assets/O-.jpg":["assets/O-.jpg"],"assets/Oneg.jpg":["assets/Oneg.jpg"],"assets/RCB.jpg":["assets/RCB.jpg"],"assets/Reset.jpg":["assets/Reset.jpg"],"assets/apna.jpg":["assets/apna.jpg"],"assets/athar.jpg":["assets/athar.jpg"],"assets/background.jpg":["assets/background.jpg"],"assets/bag.jpg":["assets/bag.jpg"],"assets/bg.jpg":["assets/bg.jpg"],"assets/bg1.jpg":["assets/bg1.jpg"],"assets/bg2.jpg":["assets/bg2.jpg"],"assets/email.jpg":["assets/email.jpg"],"assets/icon.jpg":["assets/icon.jpg"],"assets/iconbd.jpg":["assets/iconbd.jpg"],"assets/logobd1.jpg":["assets/logobd1.jpg"],"assets/logobd2.jpg":["assets/logobd2.jpg"],"assets/otp.jpg":["assets/otp.jpg"],"assets/re.jpg":["assets/re.jpg"],"assets/sanjivni.jpg":["assets/sanjivni.jpg"],"assets/sarla.jpg":["assets/sarla.jpg"],"assets/shakti.jpg":["assets/shakti.jpg"],"assets/shourya.jpg":["assets/shourya.jpg"],"assets/stack.png":["assets/stack.png"],"assets/varify.jpg":["assets/varify.jpg"],"assets/vijayee.jpg":["assets/vijayee.jpg"],"packages/cupertino_icons/assets/CupertinoIcons.ttf":["packages/cupertino_icons/assets/CupertinoIcons.ttf"]}